benchmarks/.gitignore
benchmarks/README.md
benchmarks/__init__.py
benchmarks/bench_utils.py
benchmarks/imports.py
benchmarks/lexer.py
benchmarks/microbenchmarks.py
benchmarks/parser.py
benchmarks/printer.py
benchmarks/rewriting.py
benchmarks/verifier.py
benchmarks/warmed_timeit.py
benchmarks/workloads.py
docs/.nav.yml
docs/index.md
docs/Toy/Toy_Ch0.ipynb
docs/Toy/Toy_Ch1.ipynb
docs/Toy/Toy_Ch2.ipynb
docs/Toy/Toy_Ch3.ipynb
docs/Toy/examples/ast.toy
docs/Toy/examples/codegen.toy
docs/Toy/examples/interpret.toy
docs/Toy/examples/lit.cfg
docs/Toy/examples/scalar.toy
docs/Toy/examples/tests/infer_shapes.mlir
docs/Toy/examples/tests/inline.mlir
docs/Toy/examples/tests/optimise_toy.mlir
docs/Toy/toy/__init__.py
docs/Toy/toy/__main__.py
docs/Toy/toy/compiler.py
docs/Toy/toy/interpreter.py
docs/Toy/toy/dialects/__init__.py
docs/Toy/toy/dialects/toy.py
docs/Toy/toy/emulator/__init__.py
docs/Toy/toy/emulator/toy_accelerator_instruction_functions.py
docs/Toy/toy/frontend/__init__.py
docs/Toy/toy/frontend/ir_gen.py
docs/Toy/toy/frontend/lexer.py
docs/Toy/toy/frontend/location.py
docs/Toy/toy/frontend/parser.py
docs/Toy/toy/frontend/toy_ast.py
docs/Toy/toy/rewrites/__init__.py
docs/Toy/toy/rewrites/inline_toy.py
docs/Toy/toy/rewrites/lower_toy.py
docs/assets/img/logos/Logo.png
docs/assets/img/logos/Logo.svg
docs/assets/img/logos/xdsl-transparent-single.png
docs/assets/img/logos/xdsl-transparent.png
docs/assets/img/logos/xdsl.png
docs/guides/mlir_interoperation.md
docs/marimo/README.md
docs/marimo/builders.py
docs/marimo/defining_dialects.py
docs/marimo/eqsat.py
docs/marimo/expressions.py
docs/marimo/ir_gen.py
docs/marimo/irdl.py
docs/marimo/linalg_snitch.py
docs/marimo/mlir_interoperation.py
docs/marimo/mlir_introduction.py
docs/marimo/mlir_ir.py
docs/marimo/pattern_rewrites.py
docs/marimo/pdl.py
docs/marimo/rewrite_exercises.py
docs/marimo/riscv_dialects.py
docs/marimo/source.mlir
docs/marimo/traversing_ir.py
docs/marimo/xdsl_introduction.py
docs/stylesheets/extra.css
xdsl-0.56.2.dist-info/licenses/LICENSE
xdsl-0.56.2.dist-info/METADATA
xdsl-0.56.2.dist-info/WHEEL
xdsl-0.56.2.dist-info/entry_points.txt
xdsl-0.56.2.dist-info/top_level.txt
xdsl-0.56.2.dist-info/RECORD
