Metadata-Version: 2.4
Name: xdsl
Version: 0.56.2
Summary: xDSL
Author-email: Mathieu Fehr <mathieu.fehr@ed.ac.uk>
License: Apache License v2.0 with LLVM Exceptions
Project-URL: Homepage, https://xdsl.dev/
Project-URL: Source Code, https://github.com/xdslproject/xdsl
Project-URL: Issue Tracker, https://github.com/xdslproject/xdsl/issues
Platform: Linux
Platform: Mac OS-X
Platform: Unix
Classifier: Programming Language :: Python :: 3
Requires-Python: >=3.10
License-File: LICENSE
Requires-Dist: immutabledict<4.2.3
Requires-Dist: typing-extensions<5,>=4.7
Requires-Dist: ordered-set==4.1.0
Provides-Extra: dev
Requires-Dist: toml<0.11; extra == "dev"
Requires-Dist: pytest-cov; extra == "dev"
Requires-Dist: coverage<8.0.0; extra == "dev"
Requires-Dist: ipykernel; extra == "dev"
Requires-Dist: pytest<8.5; extra == "dev"
Requires-Dist: nbval<0.12; extra == "dev"
Requires-Dist: filecheck==1.0.3; extra == "dev"
Requires-Dist: lit<19.0.0; extra == "dev"
Requires-Dist: marimo<0.18,>=0.17; extra == "dev"
Requires-Dist: pre-commit<5.0.0,>=4.0.0; extra == "dev"
Requires-Dist: ruff==0.14.7; extra == "dev"
Requires-Dist: nbconvert<8.0.0,>=7.7.2; extra == "dev"
Requires-Dist: textual-dev==1.8.0; extra == "dev"
Requires-Dist: pytest-asyncio==1.2.0; extra == "dev"
Requires-Dist: pyright==1.1.407; extra == "dev"
Requires-Dist: sympy==1.14.0; extra == "dev"
Provides-Extra: gui
Requires-Dist: textual<7,>=6; extra == "gui"
Requires-Dist: pyclip==0.7; extra == "gui"
Provides-Extra: llvm
Requires-Dist: llvmlite~=0.46.0; extra == "llvm"
Dynamic: license-file
